amm/__init__.py
amm/amm_app.py
amm/contracts/__init__.py
amm/contracts/amm.py
amm/contracts/config.py
amm/contracts/helpers.py
amm/tests/__init__.py
amm/tests/test_contract.py
amm/utils/__init__.py
amm/utils/account.py
amm/utils/purestake_client.py
algo_amm-0.0.2.dist-info/LICENSE
algo_amm-0.0.2.dist-info/METADATA
algo_amm-0.0.2.dist-info/WHEEL
algo_amm-0.0.2.dist-info/top_level.txt
algo_amm-0.0.2.dist-info/RECORD
