Metadata-Version: 2.1
Name: algo-amm
Version: 0.0.2
Summary: Automated Prediction Market Maker on Algorand
Home-page: https://github.com/dspytdao/Algo_AMM
Author: pfedprog
Author-email: pfedprog@gmail.com
License: UNKNOWN
Platform: UNKNOWN
Classifier: Programming Language :: Python :: 3
Classifier: License :: OSI Approved :: MIT License
Classifier: Operating System :: OS Independent
Requires-Python: >=3.6
License-File: LICENSE
Requires-Dist: pyteal
Requires-Dist: py-algorand-sdk
